pixel/__init__.py
pixel.py-1.0.2.dist-info/LICENSE
pixel.py-1.0.2.dist-info/METADATA
pixel.py-1.0.2.dist-info/WHEEL
pixel.py-1.0.2.dist-info/top_level.txt
pixel.py-1.0.2.dist-info/zip-safe
pixel.py-1.0.2.dist-info/RECORD
