Metadata-Version: 2.1
Name: pixel.py
Version: 1.0.2
Summary: Image Data Preprocessing Toolkit
Home-page: https://github.com/filipsedivy/pixel.py
Author: Filip Sedivy
Author-email: mail@filipsedivy.cz
License: Apache-2.0 License
Download-URL: https://github.com/filipsedivy/pixel.py/tarball/master
Platform: any
Classifier: Development Status :: 5 - Production/Stable
Classifier: Intended Audience :: Developers
Classifier: Intended Audience :: Science/Research
Classifier: Operating System :: OS Independent
Classifier: Programming Language :: Python :: 3
Classifier: Programming Language :: Python :: 3.5
Classifier: Programming Language :: Python :: 3.6
Classifier: Programming Language :: Python :: 3.7
Classifier: Programming Language :: Python :: 3.8
Classifier: Topic :: System
Classifier: Topic :: System :: Filesystems
Classifier: Topic :: Utilities
Requires: pillow
Requires: filetype
Requires-Python: >=3
License-File: LICENSE
